Workbook

Sheet Budget Summary
A1: DALLAS INDEPENDENT SCHOOL DISTRICT
A2: FY 2025-2026 Adopted Budget Summary
A3: All Funds
A5: REVENUE | B5: General Operating | C5: Food Service | D5: Debt Service | E5: Total
A6: Local Sources | B6: 1540524976 | C6: 2145000 | D6: 470620085 | E6: =SUM(B6:D6) -> 2013290061
A7: State Sources | B7: 166516511 | C7: 401681 | D7: 0 | E7: =SUM(B7:D7) -> 166918192
A8: Federal Sources | B8: 47649092 | C8: 115950525 | D8: 0 | E8: =SUM(B8:D8) -> 163599617
A9: Total Revenue | B9: =SUM(B6:B8) -> 1754690579 | C9: =SUM(C6:C8) -> 118497206 | D9: =SUM(D6:D8) -> 470620085 | E9: =SUM(E6:E8) -> 2343807870
A11: EXPENDITURES | B11: General Operating | C11: Food Service | D11: Debt Service | E11: Total
A12: 11 Instruction | B12: 969692104 | C12: 0 | D12: 0 | E12: =SUM(B12:D12) -> 969692104
A13: 12 Inst Resources & Media Svcs | B13: 21660742 | C13: 0 | D13: 0 | E13: =SUM(B13:D13) -> 21660742
A14: 13 Curr Dvlp & Inst Staff Dvlp | B14: 25851429 | C14: 0 | D14: 0 | E14: =SUM(B14:D14) -> 25851429
A15: 21 Inst Leadership | B15: 59516464 | C15: 0 | D15: 0 | E15: =SUM(B15:D15) -> 59516464
A16: 23 School Leadership | B16: 111907131 | C16: 0 | D16: 0 | E16: =SUM(B16:D16) -> 111907131
A17: 31 Guidance Counseling & Eval Svc | B17: 83833847 | C17: 0 | D17: 0 | E17: =SUM(B17:D17) -> 83833847
A18: 32 Social Work Svc | B18: 5523445 | C18: 0 | D18: 0 | E18: =SUM(B18:D18) -> 5523445
A19: 33 Health Svc | B19: 25635510 | C19: 0 | D19: 0 | E19: =SUM(B19:D19) -> 25635510
A20: 34 Student Transportation | B20: 66735396 | C20: 0 | D20: 0 | E20: =SUM(B20:D20) -> 66735396
A21: 35 Food Services | B21: 0 | C21: 116612549 | D21: 0 | E21: =SUM(B21:D21) -> 116612549
A22: 36 Extracurricular Activities | B22: 44469857 | C22: 0 | D22: 0 | E22: =SUM(B22:D22) -> 44469857
A23: 41 General Administration | B23: 58160756 | C23: 0 | D23: 0 | E23: =SUM(B23:D23) -> 58160756
... A31: 99 Other Intergov Charges | B31: 7098841 | C31: 0 | D31: 0 | E31: =SUM(B31:D31) -> 7098841
A32: Total Expenditures | B32: =SUM(B12:B31) -> 1883564247 | C32: =SUM(C12:C31) -> 118497206 | D32: =SUM(D12:D31) -> 431158300 | E32: =SUM(E12:E31) -> 2433219753
A34: NET CHANGE | B34: =B9-B32 -> -128873668 | C34: =C9-C32 -> 0 | D34: =D9-D32 -> 39461785 | E34: =E9-E32 -> -89411883
A36: OTHER FINANCING SOURCES/USES | E36: OTHER FINANCING SOURCES/USES
A37: Other Resources | B37: 0 | C37: 0 | D37: 7167000 | E37: =SUM(B37:D37) -> 7167000
A38: Non-operating Expenses | B38: 7167000 | C38: 0 | D38: 0 | E38: =SUM(B38:D38) -> 7167000
A39: Total Other Financing | B39: =B37-B38 -> -7167000 | C39: =C37-C38 -> 0 | D39: =D37-D38 -> 7167000 | E39: =E37-E38 -> 0

Sheet GF Revenue
A1: DALLAS ISD — General Fund Revenue Budget Comparison by Object
A2: FY 2025-2026
A4: Object | B4: Description | C4: FY25 Adopted | D4: FY26 Adopted | E4: $ Change | F4: % Change
B5: LOCAL / INTERMEDIATE REVENUE
A6: 5711 | B6: Taxes - Current Year | C6: 1352676224 | D6: 1484904976 | E6: =D6-C6 -> 132228752 | F6: =IF(C6=0,"-",E6/C6) -> 0.097753438
A7: 5712 | B7: Taxes - Prior Year | C7: 4000000 | D7: 0 | E7: =D7-C7 -> -4000000 | F7: =IF(C7=0,"-",E7/C7) -> -1
A8: 5719 | B8: Penalties & Interest | C8: 10000000 | D8: 10000000 | E8: =D8-C8 -> 0 | F8: =IF(C8=0,"-",E8/C8) -> 0
A9: 5739 | B9: Tuition And Fees From Local Sources | C9: 500000 | D9: 500000 | E9: =D9-C9 -> 0 | F9: =IF(C9=0,"-",E9/C9) -> 0
A10: 5742 | B10: Investment Earnings | C10: 44000000 | D10: 40000000 | E10: =D10-C10 -> -4000000 | F10: =IF(C10=0,"-",E10/C10) -> -0.090909091
A11: 5743 | B11: Rent Income | C11: 1100000 | D11: 1100000 | E11: =D11-C11 -> 0 | F11: =IF(C11=0,"-",E11/C11) -> 0
A12: 5744 | B12: Gifts & Bequests | C12: 20000 | D12: 20000 | E12: =D12-C12 -> 0 | F12: =IF(C12=0,"-",E12/C12) -> 0
A13: 5749 | B13: Other Revenues from Local Sources | C13: 3000000 | D13: 3000000 | E13: =D13-C13 -> 0 | F13: =IF(C13=0,"-",E13/C13) -> 0
A14: 5752 | B14: Athletics Gate Revenue | C14: 1000000 | D14: 1000000 | E14: =D14-C14 -> 0 | F14: =IF(C14=0,"-",E14/C14) -> 0
B15: Total Local/Intermediate Revenue | C15: =SUM(C6:C14) -> 1416296224 | D15: =SUM(D6:D14) -> 1540524976 | E15: =D15-C15 -> 124228752 | F15: =IF(C15=0,"-",E15/C15) -> 0.08771382
B17: STATE PROGRAM REVENUE
A18: 5811 | B18: Per Capita Apportionment | C18: 48893924 | D18: 49962838 | E18: =D18-C18 -> 1068914 | F18: =IF(C18=0,"-",E18/C18) -> 0.021861898
A19: 5812 | B19: Foundation - Salary & Operations | C19: 93504190 | D19: 32553673 | E19: =D19-C19 -> -60950517 | F19: =IF(C19=0,"-",E19/C19) -> -0.65184798
A20: 5831 | B20: TRS On-Behalf | C20: 80000000 | D20: 84000000 | E20: =D20-C20 -> 4000000 | F20: =IF(C20=0,"-",E20/C20) -> 0.05
B21: Total State Program Revenue | C21: =SUM(C18:C20) -> 222398114 | D21: =SUM(D18:D20) -> 166516511 | E21: =D21-C21 -> -55881603 | F21: =IF(C21=0,"-",E21/C21) -> -0.25126833
B23: FEDERAL PROGRAM REVENUE
A24: 5919 | B24: Revenue From Federal Sources | C24: 5000000 | D24: 5000000 | E24: =D24-C24 -> 0 | F24: =IF(C24=0,"-",E24/C24) -> 0
A25: 5928 | B25: Indirect Cost Through TEA | C25: 10000000 | D25: 10000000 | E25: =D25-C25 -> 0 | F25: =IF(C25=0,"-",E25/C25) -> 0
A26: 5931 | B26: School Health & Related Svcs | C26: 15000000 | D26: 6849092 | E26: =D26-C26 -> -8150908 | F26: =IF(C26=0,"-",E26/C26) -> -0.54339387
A27: 5939 | B27: Fed Rev By State Other Than TEA | C27: 800000 | D27: 800000 | E27: =D27-C27 -> 0 | F27: =IF(C27=0,"-",E27/C27) -> 0
A28: 5949 | B28: Misc Federal Revenue | C28: 25000000 | D28: 25000000 | E28: =D28-C28 -> 0 | F28: =IF(C28=0,"-",E28/C28) -> 0
B29: Total Federal Program Revenue | C29: =SUM(C24:C28) -> 55800000 | D29: =SUM(D24:D28) -> 47649092 | E29: =D29-C29 -> -8150908 | F29: =IF(C29=0,"-",E29/C29) -> -0.14607362
B31: TOTAL GENERAL FUND REVENUE | C31: =C15+C21+C29 -> 1694494338 | D31: =D15+D21+D29 -> 1754690579 | E31: =D31-C31 -> 60196241 | F31: =IF(C31=0,"-",E31/C31) -> 0.035524604
A34: CHART DATA
A35: Source | B35: FY25 | C35: FY26
A36: Local Sources | B36: =C15 -> 1416296224 | C36: =D15 -> 1540524976
A37: State Sources | B37: =C21 -> 222398114 | C37: =D21 -> 166516511
A38: Federal Sources | B38: =C29 -> 55800000 | C38: =D29 -> 47649092

Sheet GF Expenditures
A1: DALLAS ISD — General Fund Expenditure Budget Comparison
A2: FY 2025-2026 — By Function
A4: Func | B4: Description | C4: FY24 Actual | D4: FY25 Adopted | E4: FY26 Adopted | F4: $ Change (YoY) | G4: % Change | H4: % of Budget
A5: 11 | B5: Instruction | C5: 905070799 | D5: 985740474 | E5: 969692104 | F5: =E5-D5 -> -16048370 | G5: =IF(D5=0,"-",F5/D5) -> -0.016280523 | H5: =E5/E$24 -> 0.51481764
A6: 12 | B6: Inst Resources & Media Svcs | C6: 14457874 | D6: 22525597 | E6: 21660742 | F6: =E6-D6 -> -864855 | G6: =IF(D6=0,"-",F6/D6) -> -0.038394321 | H6: =E6/E$24 -> 0.011499869
A7: 13 | B7: Curr Dvlp & Inst Staff Dvlp | C7: 24775990 | D7: 30607293 | E7: 25851429 | F7: =E7-D7 -> -4755864 | G7: =IF(D7=0,"-",F7/D7) -> -0.15538336 | H7: =E7/E$24 -> 0.01372474
A8: 21 | B8: Instructional Leadership | C8: 48668763 | D8: 55827435 | E8: 59516464 | F8: =E8-D8 -> 3689029 | G8: =IF(D8=0,"-",F8/D8) -> 0.066079142 | H8: =E8/E$24 -> 0.031597788
A9: 23 | B9: School Leadership | C9: 118505082 | D9: 114763940 | E9: 111907131 | F9: =E9-D9 -> -2856809 | G9: =IF(D9=0,"-",F9/D9) -> -0.024892915 | H9: =E9/E$24 -> 0.059412431
A10: 31 | B10: Guidance Counseling & Eval Svc | C10: 66917348 | D10: 88710080 | E10: 83833847 | F10: =E10-D10 -> -4876233 | G10: =IF(D10=0,"-",F10/D10) -> -0.054968195 | H10: =E10/E$24 -> 0.04450809
A11: 32 | B11: Social Work Svc | C11: 1093837 | D11: 5606277 | E11: 5523445 | F11: =E11-D11 -> -82832 | G11: =IF(D11=0,"-",F11/D11) -> -0.014774868 | H11: =E11/E$24 -> 0.0029324431
A12: 33 | B12: Health Services | C12: 22761006 | D12: 25799353 | E12: 25635510 | F12: =E12-D12 -> -163843 | G12: =IF(D12=0,"-",F12/D12) -> -0.0063506631 | H12: =E12/E$24 -> 0.013610106
A13: 34 | B13: Student Transportation | C13: 72215397 | D13: 69768036 | E13: 66735396 | F13: =E13-D13 -> -3032640 | G13: =IF(D13=0,"-",F13/D13) -> -0.04346747 | H13: =E13/E$24 -> 0.035430379
A14: 36 | B14: Extracurricular Activities | C14: 50694457 | D14: 44731189 | E14: 44469857 | F14: =E14-D14 -> -261332 | G14: =IF(D14=0,"-",F14/D14) -> -0.0058422771 | H14: =E14/E$24 -> 0.023609419
A15: 41 | B15: General Administration | C15: 56684954 | D15: 61098099 | E15: 58160756 | F15: =E15-D15 -> -2937343 | G15: =IF(D15=0,"-",F15/D15) -> -0.048075849 | H15: =E15/E$24 -> 0.030878031
A16: 51 | B16: Facilities Maint/Ops | C16: 197371828 | D16: 206835488 | E16: 199865471 | F16: =E16-D16 -> -6970017 | G16: =IF(D16=0,"-",F16/D16) -> -0.033698361 | H16: =E16/E$24 -> 0.10611025
... A23: 99 | B23: Other Intergov Charges | C23: 0 | D23: 6845778 | E23: 7098841 | F23: =E23-D23 -> 253063 | G23: =IF(D23=0,"-",F23/D23) -> 0.036966288 | H23: =E23/E$24 -> 0.003768834
B24: TOTAL GENERAL FUND EXPENDITURES | C24: =SUM(C5:C23) -> 1658608422 | D24: =SUM(D5:D23) -> 1882316972 | E24: =SUM(E5:E23) -> 1883564247 | F24: =E24-D24 -> 1247275 | G24: =F24/D24 -> 0.00066262751 | H24: =E24/E24 -> 1
A26: FY 2025-2026 — By Object
A27: Object | B27: Description | C27: FY25 Adopted | D27: FY26 Adopted | E27: $ Change | F27: % Change | G27: % of Budget
A28: 6100 | B28: Payroll Costs | C28: 1454794349 | D28: 1464112663 | E28: =D28-C28 -> 9318314 | F28: =IF(C28=0,"-",E28/C28) -> 0.0064052448 | G28: =D28/D$34 -> 0.77730965
A29: 6200 | B29: Prof/Contracted Svcs | C29: 235641861 | D29: 264035889 | E29: =D29-C29 -> 28394028 | F29: =IF(C29=0,"-",E29/C29) -> 0.12049654 | G29: =D29/D$34 -> 0.14017886
A30: 6300 | B30: Supplies/Materials | C30: 136243403 | D30: 103119787 | E30: =D30-C30 -> -33123616 | F30: =IF(C30=0,"-",E30/C30) -> -0.24312088 | G30: =D30/D$34 -> 0.054747157
A31: 6400 | B31: Other Operating Costs | C31: 36673773 | D31: 35157708 | E31: =D31-C31 -> -1516065 | F31: =IF(C31=0,"-",E31/C31) -> -0.041339215 | G31: =D31/D$34 -> 0.018665521
A32: 6500 | B32: Debt Services | C32: 12852237 | D32: 12852237 | E32: =D32-C32 -> 0 | F32: =IF(C32=0,"-",E32/C32) -> 0 | G32: =D32/D$34 -> 0.00682336
A33: 6600 | B33: Capital Outlay | C33: 6111349 | D33: 4285963 | E33: =D33-C33 -> -1825386 | F33: =IF(C33=0,"-",E33/C33) -> -0.2986879 | G33: =D33/D$34 -> 0.0022754536
B34: TOTAL | C34: =SUM(C28:C33) -> 1882316972 | D34: =SUM(D28:D33) -> 1883564247 | E34: =D34-C34 -> 1247275 | F34: =E34/C34 -> 0.00066262751 | G34: =D34/D34 -> 1

Sheet Other Funds
A1: DALLAS ISD — Other Funds Summary
A2: FY 2025-2026
A4: FOOD SERVICE FUND
A5: Revenue | B5: FY24 Actual | C5: FY25 Adopted | D5: FY26 Adopted | E5: % of Budget
A6: Local | B6: 2291047 | C6: 2683072 | D6: 2145000 | E6: =D6/D$9 -> 0.018101693
A7: State | B7: 401681 | C7: 725000 | D7: 401681 | E7: =D7/D$9 -> 0.003389793
A8: Federal | B8: 103636561 | C8: 111875728 | D8: 115950525 | E8: =D8/D$9 -> 0.97850851
A9: Total Revenue | B9: =SUM(B6:B8) -> 106329289 | C9: =SUM(C6:C8) -> 115283800 | D9: =SUM(D6:D8) -> 118497206
A11: Expenditures
A12: Payroll Costs | B12: 52232743 | C12: 56703219 | D12: 54128380 | E12: =D12/D$18 -> 0.45679035
A13: Contracted Services | B13: 4284470 | C13: 5000005 | D13: 4749058 | E13: =D13/D$18 -> 0.040077384
A14: Supplies and Materials | B14: 58829690 | C14: 52026194 | D14: 57679422 | E14: =D14/D$18 -> 0.48675765
A15: Other Operating Costs | B15: 347500 | C15: 496382 | D15: 432850 | E15: =D15/D$18 -> 0.0036528287
A16: Debt Service | B16: 10478 | C16: 0 | D16: 10000 | E16: =D16/D$18 -> 8.4390175e-05
A17: Capital Outlay | B17: 1703872 | C17: 1058000 | D17: 1497496 | E17: =D17/D$18 -> 0.012637395
A18: Total Expenditures | B18: =SUM(B12:B17) -> 117408753 | C18: =SUM(C12:C17) -> 115283800 | D18: =SUM(D12:D17) -> 118497206
A21: DEBT SERVICE FUND
A22: Revenue | B22: FY24 Actual | C22: FY25 Adopted | D22: FY26 Adopted | E22: % of Budget
A23: Current Taxes | B23: 401907252 | C23: 426492633 | D23: 459120085 | E23: =D23/D$27 -> 0.97556415
A24: Delinquent Taxes | B24: -2750042 | C24: 1000000 | D24: 0 | E24: =IF(D$27=0,"-",D24/D$27) -> 0
A25: Taxes — Penalties & Interest | B25: 2863898 | C25: 2500000 | D25: 2500000 | E25: =D25/D$27 -> 0.0053121405
A26: Investment Earnings / Local | B26: 11558396 | C26: 9000000 | D26: 9000000 | E26: =D26/D$27 -> 0.019123706
A27: Total DS Revenue | B27: =SUM(B23:B26) -> 413579504 | C27: =SUM(C23:C26) -> 438992633 | D27: =SUM(D23:D26) -> 470620085
A29: Expenditures by Bond Authorization
A30: 2008 Bond Authorization (Fund 528) | D30: 78846603
A31: 2015 Bond Authorization (Fund 529) | D31: 52491300
A32: 2018 Bond Authorization (Fund 550) | D32: 6276350
A33: 2020 Bond Authorization (Fund 551) | D33: 293544047
A34: Total DS Expenditures | D34: =SUM(D30:D33) -> 431158300
A36: DS Net Change | D36: =D27-D34 -> 39461785
A39: SPECIAL REVENUE FUNDS
A40: Program | D40: FY26 Budget | E40: FTE | F40: full time equivalent
A41: Carl D. Perkins | D41: 2000000 | E41: 9
A42: Special Education Consolidated | D42: 35812600 | E42: 349.2
A43: Title I Part A: Improving Basic Program | D43: 83777856 | E43: 983.05
A44: Title II, Part A: Supporting Effective Instruction | D44: 7237451 | E44: 49.5
A45: Title III LEP, Part A | D45: 5735259 | E45: 43.15
A46: Title IV, Part A, Subpart 1 | D46: 6633057 | E46: 35.5
A47: Other Special Revenue | D47: 1402446 | E47: 15.34
A48: Grand Total Special Revenue | D48: =SUM(D41:D47) -> 142598669 | E48: =SUM(E41:E47) -> 1484.74

Sheet Enrollment
A1: DALLAS ISD — Enrollment Comparison
A2: FY 2024-2025 vs FY 2025-2026
A4: Level | B4: FY25 PEIMS Enrollment | C4: FY26 Projected Enrollment | D4: Change (#) | E4: Change (%) | F4: % of Total
A5: High School | B5: 40987 | C5: 39548 | D5: =C5-B5 -> -1439 | E5: =D5/B5 -> -0.035108693 | F5: =C5/C$8 -> 0.28270784
A6: Middle School | B6: 28787 | C6: 27875 | D6: =C6-B6 -> -912 | E6: =D6/B6 -> -0.031680967 | F6: =C6/C$8 -> 0.19926371
A7: Elementary School | B7: 70028 | C7: 72467 | D7: =C7-B7 -> 2439 | E7: =D7/B7 -> 0.034828926 | F7: =C7/C$8 -> 0.51802845
A8: TOTAL ALL CAMPUSES | B8: =SUM(B5:B7) -> 139802 | C8: =SUM(C5:C7) -> 139890 | D8: =C8-B8 -> 88 | E8: =D8/B8 -> 0.00062946167
A10: Key Enrollment Metrics
A12: GF Expenditure per Pupil
A13: FY25 Adopted | B13: ='GF Expenditures'!D24/B8 -> 13464.163
A14: FY26 Adopted | B14: ='GF Expenditures'!E24/C8 -> 13464.61
A15: Change | B15: =B14-B13 -> 0.44626936
A16: % Change | B16: =B15/B13 -> 3.3144975e-05
A18: Total All-Funds Expenditure per Pupil
A19: FY26 Adopted | B19: ='Budget Summary'!E32/C8 -> 17393.808

Sheet Scenario Analysis
A1: DALLAS ISD — Property Tax Revenue Scenario Analysis
A2: FY 2025-2026 — Impact of Taxable Appraised Value Growth Assumptions
A4: BASELINE ASSUMPTIONS
A5: FY26 Adopted Current-Year Tax Revenue | C5: ='GF Revenue'!D6 -> 1484904976
A6: Budget Assumption: Appraised Value Growth | C6: 0.05
A7: Implied Base Tax Revenue (before growth) | C7: =C5/(1+C6) -> 1.4141952e+09
A8: FY26 Non-Tax Local Revenue | C8: ='GF Revenue'!D15-'GF Revenue'!D6 -> 55620000
A9: FY26 State + Federal Revenue | C9: ='GF Revenue'!D21+'GF Revenue'!D29 -> 214165603
A10: FY26 Total GF Expenditures (held constant) | C10: ='GF Expenditures'!E24 -> 1883564247
A12: SCENARIO COMPARISON
B13: Stress | C13: Bear | D13: Moderate | E13: Adopted (Base) | F13: Bull
A14: Appraised Value Growth | B14: -0.02 | C14: 0 | D14: 0.02 | E14: 0.05 | F14: 0.08
A16: Current-Year Tax Revenue | B16: =$C$7*(1+B14) -> 1.3859113e+09 | C16: =$C$7*(1+C14) -> 1.4141952e+09 | D16: =$C$7*(1+D14) -> 1.4424791e+09 | E16: =$C$7*(1+E14) -> 1484904976 | F16: =$C$7*(1+F14) -> 1.5273308e+09
A17: Other Local Revenue | B17: =$C$8 -> 55620000 | C17: =$C$8 -> 55620000 | D17: =$C$8 -> 55620000 | E17: =$C$8 -> 55620000 | F17: =$C$8 -> 55620000
A18: Total Local Revenue | B18: =B16+B17 -> 1.4415313e+09 | C18: =C16+C17 -> 1.4698152e+09 | D18: =D16+D17 -> 1.4980991e+09 | E18: =E16+E17 -> 1540524976 | F18: =F16+F17 -> 1.5829508e+09
A19: State + Federal Revenue | B19: =$C$9 -> 214165603 | C19: =$C$9 -> 214165603 | D19: =$C$9 -> 214165603 | E19: =$C$9 -> 214165603 | F19: =$C$9 -> 214165603
A20: Total GF Revenue | B20: =B18+B19 -> 1.6556969e+09 | C20: =C18+C19 -> 1.6839808e+09 | D20: =D18+D19 -> 1.7122647e+09 | E20: =E18+E19 -> 1754690579 | F20: =F18+F19 -> 1.7971164e+09
A22: Total GF Expenditures | B22: =$C$10 -> 1883564247 | C22: =$C$10 -> 1883564247 | D22: =$C$10 -> 1883564247 | E22: =$C$10 -> 1883564247 | F22: =$C$10 -> 1883564247
A24: BUDGET SURPLUS / (DEFICIT) | B24: =B20-B22 -> -2.2786733e+08 | C24: =C20-C22 -> -1.9958343e+08 | D24: =D20-D22 -> -1.7129952e+08 | E24: =E20-E22 -> -128873668 | F24: =F20-F22 -> -86447812
A25: Deficit as % of GF Revenue | B25: =B24/B20 -> -0.13762624 | C25: =C24/C20 -> -0.11851883 | D25: =D24/D20 -> -0.10004266 | E25: =E24/E20 -> -0.073445238 | F25: =F24/F20 -> -0.048103623
A27: IMPACT ANALYSIS
A28: Tax Revenue vs Adopted | B28: =B16-E16 -> -98993665 | C28: =C16-E16 -> -70709761 | D28: =D16-E16 -> -42425856 | E28: 0 | F28: =F16-E16 -> 42425856
A29: Deficit Change vs Adopted | B29: =B24-E24 -> -98993665 | C29: =C24-E24 -> -70709761 | D29: =D24-E24 -> -42425856 | E29: 0 | F29: =F24-E24 -> 42425856
A30: Revenue per Pupil | B30: =B20/Enrollment!C8 -> 11835.706 | C30: =C20/Enrollment!C8 -> 12037.893 | D30: =D20/Enrollment!C8 -> 12240.08 | E30: =E20/Enrollment!C8 -> 12543.36 | F30: =F20/Enrollment!C8 -> 12846.64
A31: Revenue per Pupil vs Adopted | B31: =B30-E30 -> -707.65362 | C31: =C30-E30 -> -505.46687 | D31: =D30-E30 -> -303.28012 | E31: 0 | F31: =F30-E30 -> 303.28012
A33: REVENUE COVERAGE RATIO (Rev / Exp) | B33: =B20/B22 -> 0.87902333 | C33: =C20/C22 -> 0.89403949 | D33: =D20/D22 -> 0.90905565 | E33: =E20/E22 -> 0.93157989 | F33: =F20/F22 -> 0.95410413
A36: CHART DATA
A37: Scenario | B37: =B13 -> Stress | C37: =C13 -> Bear | D37: =D13 -> Moderate | E37: =E13 -> Adopted (Base) | F37: =F13 -> Bull
A38: Deficit ($M) | B38: =B24/1000000 -> -227.86733 | C38: =C24/1000000 -> -199.58343 | D38: =D24/1000000 -> -171.29952 | E38: =E24/1000000 -> -128.87367 | F38: =F24/1000000 -> -86.447812
A39: Coverage Ratio | B39: =B33 -> 0.87902333 | C39: =C33 -> 0.89403949 | D39: =D33 -> 0.90905565 | E39: =E33 -> 0.93157989 | F39: =F33 -> 0.95410413
A40: Revenue per Pupil ($K) | B40: =B30/1000 -> 11.835706 | C40: =C30/1000 -> 12.037893 | D40: =D30/1000 -> 12.24008 | E40: =E30/1000 -> 12.54336 | F40: =F30/1000 -> 12.84664

Sheet Financial Ratios
A1: DALLAS ISD — Financial Ratios & Analysis
A2: FY 2025-2026 Adopted Budget
E3: Dallas ISD’s primary source of revenue comes from local revenues, particularly property taxes. Compared to the prior academic fiscal year, local revenue increased in FY2026, reflecting continued growth in the district’s tax base and local economic activity. This indicates that the district relies heavily on property tax collections and the strength of the local economy to support operations. At the same time, state and federal revenues declined year-over-year. One possible explanation is that Dallas ISD is generating a larger share of its revenues locally, reducing its dependence on external funding support. This is also consistent with the structure of the Texas school finance system, where stronger local revenue generation may reduce state funding allocations while increasing recapture obligations. Finally, revenue per pupil increased modestly in FY2026. This suggests that the district continues to maintain stable operating resource generation per student despite ongoing budgetary pressures.
A4: REVENUE COMPOSITION
A5: Metric | B5: FY25 | C5: FY26 | D5: Trend
A6: Local Revenue % (GF) | B6: ='GF Revenue'!C15/'GF Revenue'!C31 -> 0.83582234 | C6: ='GF Revenue'!D15/'GF Revenue'!D31 -> 0.8779468 | D6: =IF(C6>B6,"▲",IF(C6<B6,"▼","▬")) -> ▲
A7: State Revenue % (GF) | B7: ='GF Revenue'!C21/'GF Revenue'!C31 -> 0.13124748 | C7: ='GF Revenue'!D21/'GF Revenue'!D31 -> 0.094897934 | D7: =IF(C7>B7,"▲",IF(C7<B7,"▼","▬")) -> ▼
A8: Federal Revenue % (GF) | B8: ='GF Revenue'!C29/'GF Revenue'!C31 -> 0.032930178 | C8: ='GF Revenue'!D29/'GF Revenue'!D31 -> 0.027155267 | D8: =IF(C8>B8,"▲",IF(C8<B8,"▼","▬")) -> ▼
A9: Property Tax % of Local Revenue | B9: ='GF Revenue'!C6/'GF Revenue'!C15 -> 0.95508002 | C9: ='GF Revenue'!D6/'GF Revenue'!D15 -> 0.96389542 | D9: =IF(C9>B9,"▲",IF(C9<B9,"▼","▬")) -> ▲
A10: GF Revenue per Pupil | B10: ='GF Revenue'!C31/Enrollment!B8 -> 12120.673 | C10: ='GF Revenue'!D31/Enrollment!C8 -> 12543.36 | D10: =IF(C10>B10,"▲",IF(C10<B10,"▼","▬")) -> ▲
A12: EXPENDITURE COMPOSITION
A13: Metric | B13: FY25 | C13: FY26 | D13: Trend | E13: Dallas ISD’s largest expenditure category is payroll, representing nearly 78% of General Fund expenditures. Based on the adopted budget, management appears committed to maintaining competitive compensation levels for teachers, staff, and other employees in order to support educational quality and operational stability. This highlights the district’s highly personnel-driven cost structure, which is typical for school districts but limits short-term financial flexibility. At the same time, the district appears aware of its projected operating deficit entering FY2026 and has implemented cost control measures across more flexible expenditure categories such as supplies, materials, and capital outlay. These adjustments are particularly important given the significant increase in WADA recapture obligations, which continue to place pressure on the operating budget. An additional point of interest is that expenditure per pupil remains above revenue per pupil. This suggests that the district is allocating more resources per student than it generates in operating revenue, contributing to the structurally negative operating position. However, it also reflects continued investment in educational services and student-related programs.
A14: Payroll % of GF Expenditures | B14: ='GF Expenditures'!C28/'GF Expenditures'!C34 -> 0.77287427 | C14: ='GF Expenditures'!D28/'GF Expenditures'!D34 -> 0.77730965 | D14: =IF(C14>B14,"▲",IF(C14<B14,"▼","▬")) -> ▲
A15: Instruction % of GF Expenditures | B15: ='GF Expenditures'!D5/'GF Expenditures'!D24 -> 0.52368463 | C15: ='GF Expenditures'!E5/'GF Expenditures'!E24 -> 0.51481764 | D15: =IF(C15>B15,"▲",IF(C15<B15,"▼","▬")) -> ▼
A16: Recapture (WADA) % of GF Expenditures | B16: ='GF Expenditures'!D21/'GF Expenditures'!D24 -> 0.031875609 | C16: ='GF Expenditures'!E21/'GF Expenditures'!E24 -> 0.055214469 | D16: =IF(C16>B16,"▲",IF(C16<B16,"▼","▬")) -> ▲
A17: GF Expenditure per Pupil | B17: ='GF Expenditures'!D24/Enrollment!B8 -> 13464.163 | C17: ='GF Expenditures'!E24/Enrollment!C8 -> 13464.61 | D17: =IF(C17>B17,"▲",IF(C17<B17,"▼","▬")) -> ▲
A18: Instruction per Pupil | B18: ='GF Expenditures'!D5/Enrollment!B8 -> 7050.9755 | C18: ='GF Expenditures'!E5/Enrollment!C8 -> 6931.8186 | D18: =IF(C18>B18,"▲",IF(C18<B18,"▼","▬")) -> ▼
A20: BUDGET HEALTH
A21: Metric | B21: FY25 | C21: FY26 | D21: Trend | E21: Dallas ISD is entering FY2026 with a projected operating deficit; however, the accounts clearly show improvement compared to FY2025, suggesting that management is actively trying to control and reduce the structural imbalance. The operating coverage ratio of 0.932x indicates that General Fund revenues can cover approximately 93.2% of expenditures. As a result, the district continues to operate with a projected deficit equivalent to 7.3% of General Fund revenues, meaning that operating income alone is not sufficient to fully cover expenditures. At the same time, the district maintains a separate and organized Debt Service Fund dedicated to debt-related obligations, including bond principal and interest payments. This structure is important because it provides a more stable mechanism to support debt repayment even while the General Fund remains under pressure. Debt service coverage remains above 1.0x, indicating that revenues allocated to the Debt Service Fund are currently sufficient to cover debt obligations. Finally, the Debt Service Fund reports a positive net change rather than a deficit, which is a positive signal for bondholders and supports the overall credit credibility of the issuer.
A22: GF Revenue vs Expenditures | B22: ='GF Revenue'!C31-'GF Expenditures'!D24 -> -187822634 | C22: ='GF Revenue'!D31-'GF Expenditures'!E24 -> -128873668 | D22: =IF(C22>B22,"▲",IF(C22<B22,"▼","▬")) -> ▲
A23: GF Revenue / GF Expenditures (Coverage) | B23: ='GF Revenue'!C31/'GF Expenditures'!D24 -> 0.90021732 | C23: ='GF Revenue'!D31/'GF Expenditures'!E24 -> 0.93157989 | D23: =IF(C23>B23,"▲",IF(C23<B23,"▼","▬")) -> ▲
A24: Adopted Budget Deficit / (Surplus) | C24: -128873668
A25: Deficit as % of GF Revenue | C25: =C24/'GF Revenue'!D31 -> -0.073445238
A27: Debt Service Coverage (DS Fund) | C27: ='Other Funds'!D27/'Other Funds'!D34 -> 1.0915251
A28: DS Fund Net Change | C28: ='Other Funds'!D36 -> 39461785
A30: RECAPTURE IMPACT
A31: WADA (Recapture) Payment | B31: 60000000 | C31: 104000000 | E31: The impact of recapture on Dallas ISD is highly significant, especially in FY2026, where recapture payments increased by approximately 73% year-over-year. Although this increase is substantial, it is largely connected to the district’s strong local revenue generation under the Texas school finance system. Because Dallas ISD relies heavily on property taxes, which represent the district’s primary revenue source, the district is considered relatively property-wealthy compared to other school districts in Texas. As a result, a larger portion of locally generated revenue must be redistributed through recapture obligations. This growing recapture burden reduces the amount of operating resources that remain within the district and places additional pressure on the General Fund. Even after excluding recapture expenditures, payroll continues to represent the largest expenditure category, highlighting the district’s highly personnel-driven operating structure.
A32: Year-over-Year Change | C32: =C31-B31 -> 44000000
A33: % Change | C33: =C32/B31 -> 0.73333333
A34: Recapture per Pupil | C34: =C31/Enrollment!C8 -> 743.44128
A35: GF Expenditures excl. Recapture | C35: ='GF Expenditures'!E24-C31 -> 1779564247
A36: Payroll % excl. Recapture | C36: ='GF Expenditures'!D28/C35 -> 0.82273661
